requests_throttled.py
requests_throttled-0.3.dist-info/DESCRIPTION.rst
requests_throttled-0.3.dist-info/METADATA
requests_throttled-0.3.dist-info/RECORD
requests_throttled-0.3.dist-info/WHEEL
requests_throttled-0.3.dist-info/metadata.json
requests_throttled-0.3.dist-info/top_level.txt
requests_throttled-0.3.dist-info/zip-safe
