Metadata-Version: 2.0
Name: requests-throttled
Version: 0.3
Summary: Throttling requests.Session.
Home-page: http://github.com/zaquest/requests_throttled
Author: zaquest
Author-email: web.elektro.net@gmail.com
License: MIT
Platform: UNKNOWN
Requires-Dist: requests
